AUTHORS
MANIFEST.in
README.rst
setup.py
django_simple_audit.egg-info/PKG-INFO
django_simple_audit.egg-info/SOURCES.txt
django_simple_audit.egg-info/dependency_links.txt
django_simple_audit.egg-info/top_level.txt
simple_audit/__init__.py
simple_audit/admin.py
simple_audit/m2m_audit.py
simple_audit/managers.py
simple_audit/middleware.py
simple_audit/models.py
simple_audit/settings.py
simple_audit/signal.py
simple_audit/tests.py
simple_audit/views.py
simple_audit/locale/cs_CZ/LC_MESSAGES/django.mo
simple_audit/locale/cs_CZ/LC_MESSAGES/django.po
simple_audit/locale/pt_BR/LC_MESSAGES/django.mo
simple_audit/locale/pt_BR/LC_MESSAGES/django.po
simple_audit/templates/admin/simple_audit/audit/change_form.html
simple_audit/templatetags/__init__.py
simple_audit/templatetags/audit.py