Metadata-Version: 1.1
Name: django-simple-audit
Version: 0.1.21
Summary: Simple audit for model instances in Django.
Home-page: https://github.com/leandrosouza/django-simple-audit
Author: Leandro Souza
Author-email: lsouzarj@gmail.com
License: BSD
Keywords: revisions versioning history audit
Platform: UNKNOWN
Classifier: Development Status :: 5 - Production/Stable
Classifier: Environment :: Web Environment
Classifier: Framework :: Django
Classifier: Intended Audience :: Developers
Classifier: License :: OSI Approved :: BSD License
Classifier: Operating System :: OS Independent
Classifier: Programming Language :: Python
Classifier: Topic :: Software Development :: Libraries :: Python Modules
Classifier: Topic :: Utilities
